smartmeter_webthing/__init__.py
smartmeter_webthing/app.py
smartmeter_webthing/meter.py
smartmeter_webthing/meter_webthing.py
smartmeter_webthing-1.2.32.dist-info/LICENSE
smartmeter_webthing-1.2.32.dist-info/METADATA
smartmeter_webthing-1.2.32.dist-info/WHEEL
smartmeter_webthing-1.2.32.dist-info/entry_points.txt
smartmeter_webthing-1.2.32.dist-info/top_level.txt
smartmeter_webthing-1.2.32.dist-info/RECORD
