Metadata-Version: 2.1
Name: smartmeter-webthing
Version: 1.2.32
Summary: Smartmeter WebThing
Author: Gregor Roth
Author-email: gregor.roth@web.de
Requires-Python: >=3.8
License-File: LICENSE
Requires-Dist: requests
Requires-Dist: webthing >=0.15.0
Requires-Dist: smllib ==1.2
Requires-Dist: importlib-metadata
Requires-Dist: pyserial
Requires-Dist: redzoo
